{"stats":{"minecraft:custom":{"minecraft:jump":49,"minecraft:time_since_rest":1230,"minecraft:leave_game":1,"minecraft:sprint_one_cm":9976,"minecraft:play_time":1230,"minecraft:damage_taken":31,"minecraft:time_since_death":1230,"minecraft:walk_one_cm":2758,"minecraft:total_world_time":1271,"minecraft:mob_kills":5,"minecraft:fall_one_cm":836,"minecraft:fly_one_cm":13013},"minecraft:used":{"minecraft:bow":12},"minecraft:picked_up":{"minecraft:porkchop":1,"minecraft:arrow":1,"minecraft:chicken":1,"minecraft:spider_eye":1,"minecraft:string":2},"minecraft:killed":{"minecraft:pig":2,"minecraft:skeleton":1,"minecraft:spider":1,"minecraft:chicken":1}},"DataVersion":3465}