{"stats":{"minecraft:mined":{"minecraft:grass":5,"minecraft:sunflower":4},"minecraft:killed":{"minecraft:chicken":2,"minecraft:cow":5},"minecraft:used":{"minecraft:stone_sword":43,"minecraft:anvil":1,"minecraft:squid_spawn_egg":1},"minecraft:custom":{"minecraft:time_since_rest":4263,"minecraft:crouch_one_cm":46,"minecraft:play_time":4263,"minecraft:sprint_one_cm":1973,"minecraft:walk_one_cm":11033,"minecraft:sneak_time":8,"minecraft:interact_with_anvil":1,"minecraft:mob_kills":13,"minecraft:jump":50,"minecraft:damage_dealt":1567,"minecraft:leave_game":1,"minecraft:time_since_death":4263,"minecraft:total_world_time":5522,"minecraft:fall_one_cm":1045,"minecraft:fly_one_cm":24497},"minecraft:picked_up":{"minecraft:feather":2,"minecraft:cooked_beef":3,"minecraft:chicken":1,"minecraft:leather":4,"minecraft:wheat_seeds":2,"minecraft:beef":2,"minecraft:sunflower":1}},"DataVersion":3465}