{"stats":{"minecraft:custom":{"minecraft:jump":91,"minecraft:time_since_rest":3042,"minecraft:damage_dealt":369,"minecraft:leave_game":3,"minecraft:play_time":3042,"minecraft:sprint_one_cm":3870,"minecraft:time_since_death":3042,"minecraft:walk_one_cm":9189,"minecraft:sneak_time":1,"minecraft:total_world_time":3930,"minecraft:mob_kills":3,"minecraft:talked_to_villager":10,"minecraft:fly_one_cm":8085},"minecraft:used":{"minecraft:diamond_sword":5,"minecraft:villager_spawn_egg":3}},"DataVersion":3465}