{"stats":{"minecraft:custom":{"minecraft:jump":303,"minecraft:time_since_rest":4089,"minecraft:leave_game":1,"minecraft:crouch_one_cm":2,"minecraft:deaths":2,"minecraft:sprint_one_cm":25000,"minecraft:play_time":5903,"minecraft:damage_taken":523,"minecraft:time_since_death":4065,"minecraft:walk_one_cm":12359,"minecraft:sneak_time":17,"minecraft:total_world_time":5929,"minecraft:fall_one_cm":11873,"minecraft:fly_one_cm":64609},"minecraft:mined":{"minecraft:grass":3},"minecraft:killed_by":{"minecraft:skeleton":2},"minecraft:picked_up":{"minecraft:wheat_seeds":1}},"DataVersion":3465}