{
  "type": "minecraft:entity",
  "pools": [
    {
      "bonus_rolls": 0.0,
      "entries": [
        {
          "type": "minecraft:item",
          "name": "minecraft:sculk_catalyst"
        }
      ],
      "rolls": 1.0
    },
    {
      "bonus_rolls": 0.0,
      "entries": [
        {
          "type": "minecraft:item",
          "functions": [
            {
              "enchantments": [
                "coolenchants:astral_teleport"
              ],
              "function": "minecraft:enchant_randomly"
            }
          ],
          "name": "minecraft:book",
          "weight": 10
        }
      ],
      "rolls": 1
    }

  ],
  "random_sequence": "minecraft:entities/warden"
}